dtool_lookup_server_dependency_graph_plugin/__init__.py
dtool_lookup_server_dependency_graph_plugin/config.py
dtool_lookup_server_dependency_graph_plugin/graph.py
dtool_lookup_server_dependency_graph_plugin/schemas.py
dtool_lookup_server_dependency_graph_plugin-0.2.0.dist-info/LICENSE
dtool_lookup_server_dependency_graph_plugin-0.2.0.dist-info/METADATA
dtool_lookup_server_dependency_graph_plugin-0.2.0.dist-info/WHEEL
dtool_lookup_server_dependency_graph_plugin-0.2.0.dist-info/entry_points.txt
dtool_lookup_server_dependency_graph_plugin-0.2.0.dist-info/top_level.txt
dtool_lookup_server_dependency_graph_plugin-0.2.0.dist-info/RECORD
