Metadata-Version: 2.1
Name: dtool-lookup-server-dependency-graph-plugin
Version: 0.2.0
Summary: dtool lookup server plugin for querying dataset dependency graphs
Home-page: https://github.com/IMTEK-Simulation/dtool-lookup-server-dependency-graph-plugin
Download-URL: https://github.com/IMTEK-Simulation/dtool-lookup-server-dependency-graph-plugin/tarball/0.2.0
Author: Johannes Hörmann
Author-email: johannes.hoermann@imtek.uni-freiburg.de
License: MIT
License-File: LICENSE
Requires-Dist: dtool-lookup-server >=0.18.0
Requires-Dist: dtoolcore >=3.17.0
Requires-Dist: dtool-lookup-server-direct-mongo-plugin >=0.2.0
